iduedu/__init__.py
iduedu/_api.py
iduedu/_config.py
iduedu/_version.py
iduedu/constants/__init__.py
iduedu/constants/highway_enums.py
iduedu/constants/network_enums.py
iduedu/constants/transport_specs.py
iduedu/modules/__init__.py
iduedu/modules/graph_builders/__init__.py
iduedu/modules/graph_builders/drive_walk_builders.py
iduedu/modules/graph_builders/intermodal_builders.py
iduedu/modules/graph_builders/public_transport_builders.py
iduedu/modules/graph_transformers.py
iduedu/modules/matrix/__init__.py
iduedu/modules/matrix/matrix_builder.py
iduedu/modules/matrix/numba_csr_matrix.py
iduedu/modules/overpass/__init__.py
iduedu/modules/overpass/overpass_cache.py
iduedu/modules/overpass/overpass_downloaders.py
iduedu/modules/overpass/overpass_parsers.py
iduedu-1.2.0.dist-info/METADATA
iduedu-1.2.0.dist-info/WHEEL
iduedu-1.2.0.dist-info/licenses/LICENSE.txt
iduedu-1.2.0.dist-info/RECORD
