Metadata-Version: 2.4
Name: iduedu
Version: 1.2.0
Summary: IduEdu is a Python package for the creation and manipulation of complex city networks from OpenStreetMap.
License: BSD-3-Clause
License-File: LICENSE.txt
Author: DDonnyy
Author-email: 63115678+DDonnyy@users.noreply.github.com
Requires-Python: >=3.11,<3.13
Classifier: License :: OSI Approved :: BSD License
Classifier: Programming Language :: Python :: 3
Classifier: Programming Language :: Python :: 3.11
Classifier: Programming Language :: Python :: 3.12
Requires-Dist: geopandas (>=1.1.0,<2.0.0)
Requires-Dist: loguru (>=0.7.3,<0.8.0)
Requires-Dist: networkx (>=3.5.0,<4.0.0)
Requires-Dist: numba (>=0.61.0,<0.62.0)
Requires-Dist: numpy (>=2.2.0,<3.0.0)
Requires-Dist: pandas (>=2.3.0,<3.0.0)
Requires-Dist: scipy (>=1.16.0,<2.0.0)
Requires-Dist: tqdm (>=4.67.0,<5.0.0)
